ubii/processing_modules/ocr/__init__.py
ubii/processing_modules/ocr/tesseract_ocr.py
ubii/processing_modules/ocr/data/__init__.py
ubii/processing_modules/ocr/data/frozen_east_text_detection.pb
ubii_processing_module_ocr-0.2.0.dist-info/LICENSE
ubii_processing_module_ocr-0.2.0.dist-info/LICENSE.rst
ubii_processing_module_ocr-0.2.0.dist-info/METADATA
ubii_processing_module_ocr-0.2.0.dist-info/WHEEL
ubii_processing_module_ocr-0.2.0.dist-info/entry_points.txt
ubii_processing_module_ocr-0.2.0.dist-info/top_level.txt
ubii_processing_module_ocr-0.2.0.dist-info/RECORD
