Metadata-Version: 2.1
Name: ubii-processing-module-ocr
Version: 0.2.0
Summary: "Ubi Interact Processing Module to perform OCR tasks via Tesseract"
Home-page: https://github.com/saggitar/ubii-interact-ocr-module.git
Author: Maximilian Schmidt
Author-email: ga97lul@mytum.de
Keywords: ocr,tesseract,ubi-interact,ubii,opencv
Classifier: Programming Language :: Python :: 3
Requires-Python: >=3.7
License-File: LICENSE
License-File: LICENSE.rst
Requires-Dist: ubii-node-python (>=0.3.0)
Requires-Dist: tesserocr (==2.5.2)
Requires-Dist: opencv-contrib-python-headless (==4.5.5.64)
Requires-Dist: Pillow (>=5.2)
Requires-Dist: Pillow-PIL (>=0.1dev)
Requires-Dist: numpy
Requires-Dist: importlib-resources ; python_version < "3.8"
Requires-Dist: typing-extensions ; python_version < "3.8"
Requires-Dist: backports.cached-property ; python_version < "3.8"
Provides-Extra: dev
Requires-Dist: setuptools-changelog (==1.0.0) ; extra == 'dev'
Provides-Extra: docs
Requires-Dist: sphinx (==5.0.2) ; extra == 'docs'
Provides-Extra: test
Requires-Dist: ubii-node-python[test] (>=0.3.0) ; extra == 'test'
Requires-Dist: pandas ; extra == 'test'
